popcornnotify/__init__.py
popcornnotify/notify.py
popcornnotify/notify_cli.py
popcornnotify-0.2.1.dist-info/METADATA
popcornnotify-0.2.1.dist-info/WHEEL
popcornnotify-0.2.1.dist-info/entry_points.txt
popcornnotify-0.2.1.dist-info/pbr.json
popcornnotify-0.2.1.dist-info/top_level.txt
popcornnotify-0.2.1.dist-info/RECORD
